carelytics/__init__.py
carelytics/claims.py
carelytics/encounter.py
carelytics/lab.py
carelytics/patient.py
carelytics/vitals.py
carelytics/data/__init__.py
carelytics/fhir/__init__.py
carelytics/fhir/fhir_analyzer.py
carelytics/fhir/fhir_mapper.py
carelytics/fhir/parser.py
carelytics/fhir/vitals.py
carelytics/models/__init__.py
carelytics/models/denial_prediction.py
carelytics/models/readmission.py
carelytics/utils/__init__.py
carelytics/utils/cleaner.py
carelytics/utils/deid.py
carelytics/utils/validator.py
carelytics-0.1.3.dist-info/licenses/LICENSE
carelytics-0.1.3.dist-info/METADATA
carelytics-0.1.3.dist-info/WHEEL
carelytics-0.1.3.dist-info/top_level.txt
carelytics-0.1.3.dist-info/RECORD
